pybreaker/__init__.py
pybreaker/py.typed
pybreaker-1.4.0.dist-info/licenses/LICENSE
pybreaker-1.4.0.dist-info/WHEEL
pybreaker-1.4.0.dist-info/METADATA
pybreaker-1.4.0.dist-info/RECORD
