Metadata-Version: 2.4
Name: pybreaker
Version: 1.4.0
Summary: Python implementation of the Circuit Breaker pattern
Keywords: design,pattern,circuit,breaker,integration
Author-email: Daniel Fernandes Martins <daniel.tritone@gmail.com>
Requires-Python: >=3.9
Classifier: Development Status :: 5 - Production/Stable
Classifier: Intended Audience :: Developers
Classifier: License :: OSI Approved :: BSD License
Classifier: Programming Language :: Python
Classifier: Programming Language :: Python :: 3
Classifier: Topic :: Software Development :: Libraries
License-File: LICENSE
Requires-Dist: pytest ; extra == "test"
Requires-Dist: mock ; extra == "test"
Requires-Dist: tornado ; extra == "test"
Requires-Dist: redis ; extra == "test"
Requires-Dist: fakeredis ; extra == "test"
Requires-Dist: types-mock ; extra == "test"
Requires-Dist: types-redis ; extra == "test"
Project-URL: Source, http://github.com/danielfm/pybreaker
Provides-Extra: test
